cursed_editor/__init__.py
cursed_editor/application.py
cursed_editor/backends.py
cursed_editor/configuration.py
cursed_editor/coordinate.py
cursed_editor/editor.py
cursed_editor/file_handlers.py
cursed_editor/immutable.py
cursed_editor/key_handler/__init__.py
cursed_editor/key_handler/actions.py
cursed_editor/key_handler/handler.py
cursed_editor/key_handler/state.py
cursed_editor/key_handler/triggers.py
cursed_editor/linear_editor.py
cursed_editor/lined_editor.py
cursed_editor/mutable_string.py
cursed_editor/tabbed_editor.py
cursed_editor/utils.py
cursed_editor/window.py
cursed_editor-0.11.0.dist-info/METADATA
cursed_editor-0.11.0.dist-info/WHEEL
cursed_editor-0.11.0.dist-info/entry_points.txt
cursed_editor-0.11.0.dist-info/RECORD
